gradientai/__init__.py
gradientai/_base_client.py
gradientai/_client.py
gradientai/_compat.py
gradientai/_constants.py
gradientai/_exceptions.py
gradientai/_files.py
gradientai/_models.py
gradientai/_qs.py
gradientai/_resource.py
gradientai/_response.py
gradientai/_streaming.py
gradientai/_types.py
gradientai/_version.py
gradientai/py.typed
gradientai/_utils/__init__.py
gradientai/_utils/_logs.py
gradientai/_utils/_proxy.py
gradientai/_utils/_reflection.py
gradientai/_utils/_resources_proxy.py
gradientai/_utils/_streams.py
gradientai/_utils/_sync.py
gradientai/_utils/_transform.py
gradientai/_utils/_typing.py
gradientai/_utils/_utils.py
gradientai/lib/.keep
gradientai/resources/__init__.py
gradientai/resources/regions.py
gradientai/resources/agents/__init__.py
gradientai/resources/agents/agents.py
gradientai/resources/agents/api_keys.py
gradientai/resources/agents/evaluation_datasets.py
gradientai/resources/agents/evaluation_runs.py
gradientai/resources/agents/evaluation_test_cases.py
gradientai/resources/agents/functions.py
gradientai/resources/agents/knowledge_bases.py
gradientai/resources/agents/routes.py
gradientai/resources/agents/versions.py
gradientai/resources/agents/chat/__init__.py
gradientai/resources/agents/chat/chat.py
gradientai/resources/agents/chat/completions.py
gradientai/resources/agents/evaluation_metrics/__init__.py
gradientai/resources/agents/evaluation_metrics/evaluation_metrics.py
gradientai/resources/agents/evaluation_metrics/workspaces/__init__.py
gradientai/resources/agents/evaluation_metrics/workspaces/agents.py
gradientai/resources/agents/evaluation_metrics/workspaces/workspaces.py
gradientai/resources/chat/__init__.py
gradientai/resources/chat/chat.py
gradientai/resources/chat/completions.py
gradientai/resources/inference/__init__.py
gradientai/resources/inference/api_keys.py
gradientai/resources/inference/inference.py
gradientai/resources/knowledge_bases/__init__.py
gradientai/resources/knowledge_bases/data_sources.py
c63a5cfe_b235_4fbe_8bbb_82a9e02a482a_python-0.1.0a13.dist-info/METADATA
c63a5cfe_b235_4fbe_8bbb_82a9e02a482a_python-0.1.0a13.dist-info/WHEEL
c63a5cfe_b235_4fbe_8bbb_82a9e02a482a_python-0.1.0a13.dist-info/licenses/LICENSE
c63a5cfe_b235_4fbe_8bbb_82a9e02a482a_python-0.1.0a13.dist-info/RECORD
